claif_cla/__init__.py
claif_cla/__version__.py
claif_cla/cli.py
claif_cla/client.py
claif_cla-1.0.31.dist-info/METADATA
claif_cla-1.0.31.dist-info/WHEEL
claif_cla-1.0.31.dist-info/entry_points.txt
claif_cla-1.0.31.dist-info/licenses/LICENSE
claif_cla-1.0.31.dist-info/RECORD
