Metadata-Version: 2.4
Name: claif_cla
Version: 1.0.31
Summary: A Claif provider for Anthropic Claude, compatible with the OpenAI Responses API.
Project-URL: Documentation, https://github.com/twardoch/claif_cla#readme
Project-URL: Issues, https://github.com/twardoch/claif_cla/issues
Project-URL: Source, https://github.com/twardoch/claif_cla
Author-email: Adam Twardoch <adam+github@twardoch.com>
License: MIT
License-File: LICENSE
Keywords: ai,anthropic,artificial-intelligence,claif,claude,cli,command-line,llm,openai,responses-api
Classifier: Development Status :: 4 - Beta
Classifier: Intended Audience :: Developers
Classifier: License :: OSI Approved :: MIT License
Classifier: Operating System :: OS Independent
Classifier: Programming Language :: Python
Classifier: Programming Language :: Python :: 3.10
Classifier: Programming Language :: Python :: 3.11
Classifier: Programming Language :: Python :: 3.12
Classifier: Programming Language :: Python :: Implementation :: CPython
Classifier: Programming Language :: Python :: Implementation :: PyPy
Requires-Python: >=3.10
Requires-Dist: anthropic>=0.18.0
Requires-Dist: httpx
Requires-Dist: loguru>=0.7.0
Requires-Dist: openai>=1.0.0
Requires-Dist: pydantic>=2.0.0
Requires-Dist: python-fire
Requires-Dist: rich>=13.9.4
Provides-Extra: all
Requires-Dist: absolufy-imports>=0.3.1; extra == 'all'
Requires-Dist: claif>=1.0.0; extra == 'all'
Requires-Dist: claude-code; extra == 'all'
Requires-Dist: claude-code-sdk>=0.0.1; extra == 'all'
Requires-Dist: coverage[toml]>=7.6.12; extra == 'all'
Requires-Dist: fire>=0.5.0; extra == 'all'
Requires-Dist: isort>=6.0.1; extra == 'all'
Requires-Dist: loguru>=0.7.0; extra == 'all'
Requires-Dist: mypy>=1.15.0; extra == 'all'
Requires-Dist: myst-parser>=4.0.1; extra == 'all'
Requires-Dist: pre-commit>=4.1.0; extra == 'all'
Requires-Dist: pytest-asyncio>=0.26.0; extra == 'all'
Requires-Dist: pytest-benchmark[histogram]>=5.1.0; extra == 'all'
Requires-Dist: pytest-cov>=6.0.0; extra == 'all'
Requires-Dist: pytest-fixture-config<=1.8.0; extra == 'all'
Requires-Dist: pytest-xdist>=3.6.1; extra == 'all'
Requires-Dist: pytest>=8.3.4; extra == 'all'
Requires-Dist: pyupgrade>=3.19.1; extra == 'all'
Requires-Dist: rich>=13.9.4; extra == 'all'
Requires-Dist: ruff>=0.9.7; extra == 'all'
Requires-Dist: sphinx-autodoc-typehints>=3.2.0; extra == 'all'
Requires-Dist: sphinx-rtd-theme>=3.0.2; extra == 'all'
Requires-Dist: sphinx>=8.2.3; extra == 'all'
Provides-Extra: dev
Requires-Dist: absolufy-imports>=0.3.1; extra == 'dev'
Requires-Dist: isort>=6.0.1; extra == 'dev'
Requires-Dist: mypy>=1.15.0; extra == 'dev'
Requires-Dist: pre-commit>=4.1.0; extra == 'dev'
Requires-Dist: pyupgrade>=3.19.1; extra == 'dev'
Requires-Dist: ruff>=0.9.7; extra == 'dev'
Provides-Extra: docs
Requires-Dist: myst-parser>=4.0.1; extra == 'docs'
Requires-Dist: sphinx-autodoc-typehints>=3.2.0; extra == 'docs'
Requires-Dist: sphinx-rtd-theme>=3.0.2; extra == 'docs'
Requires-Dist: sphinx>=8.2.3; extra == 'docs'
Provides-Extra: test
Requires-Dist: coverage[toml]>=7.6.12; extra == 'test'
Requires-Dist: pytest-asyncio>=0.26.0; extra == 'test'
Requires-Dist: pytest-benchmark[histogram]>=5.1.0; extra == 'test'
Requires-Dist: pytest-cov>=6.0.0; extra == 'test'
Requires-Dist: pytest-fixture-config<=1.8.0; extra == 'test'
Requires-Dist: pytest-xdist>=3.6.1; extra == 'test'
Requires-Dist: pytest>=8.3.4; extra == 'test'
